meteoshrooms/__init__.py
meteoshrooms/constants.py
meteoshrooms/dashboard/__init__.py
meteoshrooms/dashboard/constants.py
meteoshrooms/dashboard/dashboard.py
meteoshrooms/dashboard/dashboard_map.py
meteoshrooms/dashboard/dashboard_timeseries_chart.py
meteoshrooms/dashboard/dashboard_utils.py
meteoshrooms/dashboard/log.py
meteoshrooms/dashboard/settings.py
meteoshrooms/dashboard/ux_metrics.py
meteoshrooms/data_preparation/__init__.py
meteoshrooms/data_preparation/constants.py
meteoshrooms/data_preparation/data_preparation.py
meteoshrooms/py.typed
meteoshrooms-0.3.1.dist-info/WHEEL
meteoshrooms-0.3.1.dist-info/entry_points.txt
meteoshrooms-0.3.1.dist-info/METADATA
meteoshrooms-0.3.1.dist-info/RECORD
