Metadata-Version: 2.4
Name: MeteoShrooms
Version: 0.3.1
Summary: Dashboard with Key Mushroom Metrics (KMM)
Keywords: Fungi,Mushrooms,Dashboard,Meteo,Metrics
Author: Peter Zweifel
License-Expression: CC-BY-NC-SA-4.0
Requires-Dist: plotly>=6.3.0
Requires-Dist: polars>=1.32.3
Requires-Dist: streamlit>=1.52.1
Requires-Dist: typer>=0.20.0
Requires-Python: >=3.13
